{"status":"done","publicPath":"/static/dist/","chunks":{"application":[{"name":"js/application.3c30157a.js","publicPath":"/static/dist/js/application.3c30157a.js","path":"static/dist/js/application.3c30157a.js"},{"name":"js/application.3c30157a.js.map","publicPath":"/static/dist/js/application.3c30157a.js.map","path":"static/dist/js/application.3c30157a.js.map"}],"chunk-common":[{"name":"js/chunk-common.e7941aaa.js","publicPath":"/static/dist/js/chunk-common.e7941aaa.js","path":"static/dist/js/chunk-common.e7941aaa.js"},{"name":"js/chunk-common.e7941aaa.js.map","publicPath":"/static/dist/js/chunk-common.e7941aaa.js.map","path":"static/dist/js/chunk-common.e7941aaa.js.map"}],"main":[{"name":"css/main.0141eb30.css","publicPath":"/static/dist/css/main.0141eb30.css","path":"static/dist/css/main.0141eb30.css"},{"name":"js/main.8272c3ff.js","publicPath":"/static/dist/js/main.8272c3ff.js","path":"static/dist/js/main.8272c3ff.js"},{"name":"css/main.0141eb30.css.map","publicPath":"/static/dist/css/main.0141eb30.css.map","path":"static/dist/css/main.0141eb30.css.map"},{"name":"js/main.8272c3ff.js.map","publicPath":"/static/dist/js/main.8272c3ff.js.map","path":"static/dist/js/main.8272c3ff.js.map"}],"rich_text_editor":[{"name":"js/rich_text_editor.0d2d7a89.js","publicPath":"/static/dist/js/rich_text_editor.0d2d7a89.js","path":"static/dist/js/rich_text_editor.0d2d7a89.js"},{"name":"js/rich_text_editor.0d2d7a89.js.map","publicPath":"/static/dist/js/rich_text_editor.0d2d7a89.js.map","path":"static/dist/js/rich_text_editor.0d2d7a89.js.map"}],"test":[{"name":"js/test.2ff30b1f.js","publicPath":"/static/dist/js/test.2ff30b1f.js","path":"static/dist/js/test.2ff30b1f.js"},{"name":"js/test.2ff30b1f.js.map","publicPath":"/static/dist/js/test.2ff30b1f.js.map","path":"static/dist/js/test.2ff30b1f.js.map"}],"vue_app":[{"name":"css/vue_app.a5809ddf.css","publicPath":"/static/dist/css/vue_app.a5809ddf.css","path":"static/dist/css/vue_app.a5809ddf.css"},{"name":"js/vue_app.397a2cfa.js","publicPath":"/static/dist/js/vue_app.397a2cfa.js","path":"static/dist/js/vue_app.397a2cfa.js"},{"name":"css/vue_app.a5809ddf.css.map","publicPath":"/static/dist/css/vue_app.a5809ddf.css.map","path":"static/dist/css/vue_app.a5809ddf.css.map"},{"name":"js/vue_app.397a2cfa.js.map","publicPath":"/static/dist/js/vue_app.397a2cfa.js.map","path":"static/dist/js/vue_app.397a2cfa.js.map"}]}}